.gitignore
AUTHORS.txt
COPYING.txt
MANIFEST.in
Makefile
README.txt
TODO.txt
setup.cfg
setup.py
docs/guide.txt
examples/arabidopsis.psel
examples/arabidopsis.txt
pipviewer/ProbesListDialog.py
pipviewer/ProbesListGui.py
pipviewer/ScoreGui.py
pipviewer/SpeciesGenomesDialog.py
pipviewer/SpeciesGenomesGui.py
pipviewer/UserManuelGui.py
pipviewer/ViewerGui.py
pipviewer/ViewerWidget.py
pipviewer/__init__.py
pipviewer/config.py
pipviewer/guide.html
pipviewer/probeAlign.py
pipviewer/pselfiles.py
pipviewer/utils.py
pipviewer/viewer_app.py
pipviewer.egg-info/PKG-INFO
pipviewer.egg-info/SOURCES.txt
pipviewer.egg-info/dependency_links.txt
pipviewer.egg-info/entry_points.txt
pipviewer.egg-info/not-zip-safe
pipviewer.egg-info/requires.txt
pipviewer.egg-info/top_level.txt
pipviewer/scripts/__init__.py
pipviewer/scripts/pippacker.py
ui/probeslistgui.ui
ui/scoregui.ui
ui/speciesgenomesgui.ui
ui/usermanuelgui.ui
ui/viewergui.ui
