Metadata-Version: 1.0
Name: pipviewer
Version: 0.3.9
Summary: graphically display conservation on a multiple alignment
Home-page: http://ygingras.net/bioinfo
Author: Yannick Gingras
Author-email: ygingras@ygingras.net
License: GPLv3 or later
Platform: UNKNOWN
